solvemail/__init__.py
solvemail/auth.py
solvemail/core.py
solvemail/msg.py
solvemail-0.1.8.dist-info/METADATA
solvemail-0.1.8.dist-info/WHEEL
solvemail-0.1.8.dist-info/RECORD
