Metadata-Version: 2.4
Name: solvemail
Version: 0.1.8
Summary: A fastai-style Gmail API client with convenient read/write support
Author: Answer.AI
License: Apache-2.0
Requires-Python: >=3.10
Requires-Dist: beautifulsoup4>=4.12.0
Requires-Dist: fastcore>=1.7.0
Requires-Dist: google-api-python-client>=2.120.0
Requires-Dist: google-auth-httplib2>=0.2.0
Requires-Dist: google-auth-oauthlib>=1.2.0
Requires-Dist: google-auth>=2.30.0
Requires-Dist: httpx>=0.27.0
Requires-Dist: mistletoe>=1.3.0
Provides-Extra: dev
Requires-Dist: pytest-timeout>=2.2.0; extra == 'dev'
Requires-Dist: pytest>=8.0.0; extra == 'dev'
